tests/__init__.py
tests/test_cellCompVolume_payload.py
tests/test_cli.py
tests/test_customize_pipeline.py
tests/test_metadata.py
tests/validate_atlas_release.py
tests/data/annotation_leaves_only.nrrd
tests/data/hierarchy_leaves_only.json
tests/data/output.nrrd
tests/data/output_expected.nrrd
tests/data/output_315/output.nrrd
tests/data/output_549/output.nrrd
blue_brain_atlas_pipeline-2.0.1.dist-info/AUTHORS.txt
blue_brain_atlas_pipeline-2.0.1.dist-info/LICENSE.txt
blue_brain_atlas_pipeline-2.0.1.dist-info/METADATA
blue_brain_atlas_pipeline-2.0.1.dist-info/WHEEL
blue_brain_atlas_pipeline-2.0.1.dist-info/entry_points.txt
blue_brain_atlas_pipeline-2.0.1.dist-info/top_level.txt
blue_brain_atlas_pipeline-2.0.1.dist-info/RECORD
